{
	"frame": {
		"name": "Neynar checker",
		"version": "1",
		"iconUrl": "https://neynar-checker.vercel.app/icon.png",
		"homeUrl": "https://neynar-checker.vercel.app",
		"imageUrl": "https://neynar-checker.vercel.app/image.png",
		"buttonTitle": "Check Score",
		"splashImageUrl": "https://neynar-checker.vercel.app/splash.png",
		"splashBackgroundColor": "#080508",
		"webhookUrl": "https://neynar-checker.vercel.app/api/webhook",
		"subtitle": "Check your neynar score",
		"description": "Neynar score reveals the quality of user account",
		"primaryCategory": "utility",
		"ogTitle": "Neynar Checker"
	},
	"accountAssociation": {
		"header": "",
		"payload": "",
		"signature": ""
	}
}
